pycraf/__init__.py
pycraf/_compiler.c
pycraf/compiler_version.cpython-311-darwin.so
pycraf/conftest.py
pycraf/init_testrunner.py
pycraf/version.py
pycraf/antenna/__init__.py
pycraf/antenna/cyantenna.c
pycraf/antenna/cyantenna.cpython-311-darwin.so
pycraf/antenna/cyantenna.pyx
pycraf/antenna/fixedlink.py
pycraf/antenna/imt.py
pycraf/antenna/ras.py
pycraf/antenna/setup_package.py
pycraf/antenna/tests/__init__.py
pycraf/antenna/tests/test_antenna.py
pycraf/atm/__init__.py
pycraf/atm/atm.py
pycraf/atm/atm_helper.c
pycraf/atm/atm_helper.cpython-311-darwin.so
pycraf/atm/atm_helper.pyx
pycraf/atm/setup_package.py
pycraf/atm/tests/__init__.py
pycraf/atm/tests/setup_package.py
pycraf/atm/tests/test_atm.py
pycraf/atm/tests/data/atm_layers.npz
pycraf/conversions/__init__.py
pycraf/conversions/conversions.py
pycraf/conversions/tests/__init__.py
pycraf/conversions/tests/test_conversions.py
pycraf/geometry/__init__.py
pycraf/geometry/cygeometry.c
pycraf/geometry/cygeometry.cpython-311-darwin.so
pycraf/geometry/cygeometry.pyx
pycraf/geometry/geometry.py
pycraf/geometry/setup_package.py
pycraf/geometry/tests/__init__.py
pycraf/geometry/tests/setup_package.py
pycraf/geometry/tests/test_geometry.py
pycraf/geometry/tests/data/rotmat_cases.npz
pycraf/geospatial/__init__.py
pycraf/geospatial/geospatial.py
pycraf/geospatial/tests/__init__.py
pycraf/geospatial/tests/setup_package.py
pycraf/geospatial/tests/test_geospatial.py
pycraf/geospatial/tests/data/wgs84_etrs89.npz
pycraf/geospatial/tests/data/wgs84_gauss_kruger_epsg31467.npz
pycraf/geospatial/tests/data/wgs84_itrf2005.npz
pycraf/geospatial/tests/data/wgs84_itrf2008.npz
pycraf/geospatial/tests/data/wgs84_utm_zone1N.npz
pycraf/geospatial/tests/data/wgs84_utm_zone32N.npz
pycraf/geospatial/tests/data/wgs84_utm_zone60N.npz
pycraf/itudata/LICENSE.ITU
pycraf/itudata/README.md
pycraf/itudata/p.452-16/make_npy.py
pycraf/itudata/p.452-16/refract_map.npz
pycraf/itudata/p.452-16/R-REC-P.452-16-201507/DN50.TXT
pycraf-2.1.0.dist-info/COPERNICUS.EU
pycraf-2.1.0.dist-info/COPYING
pycraf-2.1.0.dist-info/LICENSE.ITU
pycraf-2.1.0.dist-info/LICENSE_ASTROPY_PACKAGE_TEMPLATE.rst
pycraf-2.1.0.dist-info/METADATA
pycraf-2.1.0.dist-info/README.rst
pycraf-2.1.0.dist-info/WHEEL
pycraf-2.1.0.dist-info/top_level.txt
pycraf-2.1.0.dist-info/RECORD
