Metadata-Version: 2.2
Name: pycraf
Version: 2.1.0
Summary: pycraf - compatibility studies for radio astronomy spectrum management
Author-email: Benjamin Winkel <bwinkel@mpifr.de>
License: GPLv3
Project-URL: Homepage, https://pypi.org/project/pycraf/
Project-URL: Documentation, https://bwinkel.github.io/pycraf/
Project-URL: Repository, https://github.com/bwinkel/pycraf
Project-URL: Issues, https://github.com/bwinkel/pycraf/issues
Project-URL: Changelog, https://github.com/bwinkel/pycraf/CHANGES.rst
Keywords: astronomy,astrophysics,radio astronomy,spectrum management,compatibility studies
Classifier: Intended Audience :: Science/Research
Classifier: Operating System :: OS Independent
Classifier: License :: OSI Approved :: GNU General Public License v3 (GPLv3)
Classifier: License :: OSI Approved :: Apache Software License
Classifier: License :: OSI Approved :: BSD License
Classifier: Programming Language :: C
Classifier: Programming Language :: Cython
Classifier: Programming Language :: Python :: 3 :: Only
Classifier: Programming Language :: Python :: Implementation :: CPython
Classifier: Topic :: Scientific/Engineering :: Astronomy
Classifier: Topic :: Scientific/Engineering :: Physics
Classifier: Topic :: Scientific/Engineering :: GIS
Requires-Python: >=3.8
License-File: licenses/COPERNICUS.EU
License-File: licenses/COPYING
License-File: licenses/LICENSE.ITU
License-File: licenses/LICENSE_ASTROPY_PACKAGE_TEMPLATE.rst
License-File: licenses/README.rst
Requires-Dist: astropy
Requires-Dist: build
Requires-Dist: ipdb
Requires-Dist: matplotlib
Requires-Dist: numpy
Requires-Dist: pip
Requires-Dist: pyproj
Requires-Dist: pytest
Requires-Dist: pytest-astropy
Requires-Dist: pytest-doctestplus
Requires-Dist: pytest-remotedata
Requires-Dist: rasterio
Requires-Dist: scipy
Requires-Dist: setuptools
Requires-Dist: setuptools-scm
Requires-Dist: sgp4
Requires-Dist: twine
Requires-Dist: wheel
Provides-Extra: test
Requires-Dist: pytest>=7.0; extra == "test"
Requires-Dist: pytest-astropy>=0.10; extra == "test"
Requires-Dist: pytest-doctestplus; extra == "test"
Requires-Dist: pytest-remotedata; extra == "test"
Provides-Extra: recommended
Requires-Dist: cartopy; extra == "recommended"
Requires-Dist: ffmpeg; extra == "recommended"
Requires-Dist: fiona; extra == "recommended"
Requires-Dist: geopandas; extra == "recommended"
Requires-Dist: h5py; extra == "recommended"
Requires-Dist: openpyxl; extra == "recommended"
Requires-Dist: osmnx; extra == "recommended"
Requires-Dist: pandas; extra == "recommended"
Requires-Dist: reproject; extra == "recommended"
Requires-Dist: shapely; extra == "recommended"
Requires-Dist: tqdm; extra == "recommended"
Provides-Extra: docs
Requires-Dist: sphinx; extra == "docs"
Requires-Dist: sphinx-astropy[confv2]; extra == "docs"
Requires-Dist: sphinx-copybutton; extra == "docs"
Requires-Dist: pydata-sphinx-theme; extra == "docs"
Requires-Dist: sphinx-design; extra == "docs"
Requires-Dist: pytest>=7.0; extra == "docs"
